pydaikin/__init__.py
pydaikin/daikin_airbase.py
pydaikin/daikin_base.py
pydaikin/daikin_brp069.py
pydaikin/daikin_brp072c.py
pydaikin/daikin_brp084.py
pydaikin/daikin_skyfi.py
pydaikin/discovery.py
pydaikin/exceptions.py
pydaikin/factory.py
pydaikin/power.py
pydaikin/response.py
pydaikin/values.py
pydaikin-2.17.0.data/scripts/pydaikin
pydaikin-2.17.0.dist-info/licenses/LICENSE
pydaikin-2.17.0.dist-info/METADATA
pydaikin-2.17.0.dist-info/WHEEL
pydaikin-2.17.0.dist-info/top_level.txt
pydaikin-2.17.0.dist-info/RECORD
