Metadata-Version: 2.4
Name: pydaikin
Version: 2.17.0
Summary: Python Daikin HVAC appliances interface
Author-email: Fredrik Erlandsson <fredrik.e@gmail.com>, Yari Adan <mustang@yadan.org>
Maintainer-email: Fredrik Erlandsson <fredrik.e@gmail.com>, Matthias Lemainque <matthias.lemainque+pydaikin@gmail.com>
License-Expression: GPL-3.0-or-later
Project-URL: Homepage, https://github.com/fredrike/pydaikin
Project-URL: Repository, https://github.com/fredrike/pydaikin.git
Project-URL: Issues, https://github.com/fredrike/pydaikin/issues
Classifier: Programming Language :: Python :: 3
Classifier: Operating System :: OS Independent
Classifier: Topic :: Software Development :: Libraries :: Application Frameworks
Classifier: Topic :: Home Automation
Requires-Python: >=3.12
License-File: LICENSE
Requires-Dist: netifaces
Requires-Dist: aiohttp
Requires-Dist: urllib3
Requires-Dist: tenacity
Dynamic: license-file
